pfly/__init__.py
pfly/cli.py
pfly/file_collector.py
pfly/linter.py
pfly/violation.py
pfly/policies/__init__.py
pfly/policies/base.py
pfly/policies/consistent_kv.py
pfly/policies/exception_exc_info.py
pfly/policies/log_loop.py
pfly/presenters/__init__.py
pfly/presenters/base.py
pfly/presenters/cli.py
pfly-0.1.1.dist-info/METADATA
pfly-0.1.1.dist-info/WHEEL
pfly-0.1.1.dist-info/entry_points.txt
pfly-0.1.1.dist-info/licenses/LICENSE
pfly-0.1.1.dist-info/RECORD
