Metadata-Version: 2.4
Name: pfly
Version: 0.1.1
Summary: pfly - Python LOggling Linter
License-File: LICENSE
Requires-Python: >=3.9
Requires-Dist: colorama>=0.4.6
Requires-Dist: jsonschema>=4.0.0
Requires-Dist: libcst>=1.0.0
Requires-Dist: pyyaml>=6.0
